thumbor_dash/__init__.py
thumbor_dash/app.py
thumbor_dash/context.py
thumbor_dash/crypto.py
thumbor_dash/server.py
thumbor_dash/testing.py
thumbor_dash/url.py
thumbor_dash/url_composer.py
thumbor_dash/utils.py
thumbor_dash/dapiclient/__init__.py
thumbor_dash/dapiclient/dapiclient.py
thumbor_dash/error_handlers/__init__.py
thumbor_dash/error_handlers/sentry.py
thumbor_dash/handler_lists/__init__.py
thumbor_dash/handler_lists/upload.py
thumbor_dash/handlers/__init__.py
thumbor_dash/handlers/image_resource.py
thumbor_dash/handlers/imaging.py
thumbor_dash/storages/__init__.py
thumbor_dash/storages/request_storage.py
thumbor_dash/url_signers/__init__.py
thumbor_dash/url_signers/base64_hmac_sha256.py
thumbor_dash/verifiers/__init__.py
thumbor_dash/verifiers/access_status_verifier.py
thumbor_dash/verifiers/image_size_verifier.py
thumbor_dash/verifiers/thumbnail_size_verifier.py
thumbor_dash/verifiers/url_field_verifier.py
thumbor_dash-0.0.20.dist-info/LICENSE
thumbor_dash-0.0.20.dist-info/METADATA
thumbor_dash-0.0.20.dist-info/WHEEL
thumbor_dash-0.0.20.dist-info/entry_points.txt
thumbor_dash-0.0.20.dist-info/top_level.txt
thumbor_dash-0.0.20.dist-info/RECORD
