Metadata-Version: 2.1
Name: thumbor-dash
Version: 0.0.20
Summary: A thumbor server extension for DASH
Home-page: https://github.com/mayoreee/thumbor_dash
Author: mayoreee
Project-URL: Source Code, https://github.com/mayoreee/thumbor_dash
Project-URL: Bug Tracker, https://github.com/mayoreee/thumbor_dash/issues
Classifier: Programming Language :: Python :: 3
Classifier: License :: OSI Approved :: MIT License
Requires-Python: >=3.9
License-File: LICENSE
Requires-Dist: thumbor (>="7.0.0")
Requires-Dist: dapiclient (>="0.0.6")
Requires-Dist: grpcio (>="1.38.1")
